<data><Label>LPrev</Label><FPS>7</FPS><Frame><Avg_x>333</Avg_x><Avg_y>267</Avg_y><Avg_dist>178.87210068889488</Avg_dist><Keypoint><ID>0</ID><X>0.024532009319036617</X><Y>-0.7487254925098836</Y><Confidence>0.81516594</Confidence></Keypoint><Keypoint><ID>1</ID><X>0.012298847309470074</X><Y>0.010778189963911142</Y><Confidence>0.57389677</Confidence></Keypoint><Keypoint><ID>2</ID><X>-0.49793603178274476</X><Y>0.047256052084624564</Y><Confidence>0.50244534</Confidence></Keypoint><Keypoint><ID>3</ID><X>-0.7167698500235677</X><Y>0.6364767365605791</Y><Confidence>0.217971</Confidence></Keypoint><Keypoint><ID>4</ID><X>-1.8616653950924054</X><Y>-1.4926866681371538</Y><Confidence>0.0</Confidence></Keypoint><Keypoint><ID>5</ID><X>0.49844206450875483</X><Y>-0.03777740739179189</Y><Confidence>0.35533178</Confidence></Keypoint><Keypoint><ID>6</ID><X>0.7717178213380645</X><Y>0.6547720546121517</Y><Confidence>0.17144087</Confidence></Keypoint><Keypoint><ID>7</ID><X>-1.8616653950924054</X><Y>-1.4926866681371538</Y><Confidence>0.0</Confidence></Keypoint><Keypoint><ID>8</ID><X>-1.8616653950924054</X><Y>-1.4926866681371538</Y><Confidence>0.0</Confidence></Keypoint><Keypoint><ID>9</ID><X>-1.8616653950924054</X><Y>-1.4926866681371538</Y><Confidence>0.0</Confidence></Keypoint><Keypoint><ID>10</ID><X>-1.8616653950924054</X><Y>-1.4926866681371538</Y><Confidence>0.0</Confidence></Keypoint><Keypoint><ID>11</ID><X>-1.8616653950924054</X><Y>-1.4926866681371538</Y><Confidence>0.0</Confidence></Keypoint><Keypoint><ID>12</ID><X>-1.8616653950924054</X><Y>-1.4926866681371538</Y><Confidence>0.0</Confidence></Keypoint><Keypoint><ID>13</ID><X>-1.8616653950924054</X><Y>-1.4926866681371538</Y><Confidence>0.0</Confidence></Keypoint><Keypoint><ID>14</ID><X>-0.09080114064145238</X><Y>-0.8457784661600116</Y><Confidence>0.9385736</Confidence></Keypoint><Keypoint><ID>15</ID><X>0.15179651013187306</X><Y>-0.8458892354612125</Y><Confidence>0.88069546</Confidence></Keypoint><Keypoint><ID>16</ID><X>-0.2246333183887992</X><Y>-0.730267070181148</Y><Confidence>0.76385987</Confidence></Keypoint><Keypoint><ID>17</ID><X>0.29192048655413544</X><Y>-0.7304237765394893</Y><Confidence>0.75544995</Confidence></Keypoint></Frame><Frame><Avg_x>330</Avg_x><Avg_y>271</Avg_y><Avg_dist>183.5906724011389</Avg_dist><Keypoint><ID>0</ID><X>0.034346154205178225</X><Y>-0.7335521071065345</Y><Confidence>0.8289398</Confidence></Keypoint><Keypoint><ID>1</ID><X>0.022518994509245847</X><Y>0.0063629723545782285</Y><Confidence>0.57904845</Confidence></Keypoint><Keypoint><ID>2</ID><X>-0.492397383091832</X><Y>0.05366147134067381</Y><Confidence>0.5057148</Confidence></Keypoint><Keypoint><ID>3</ID><X>-0.7291440378679211</X><Y>0.6872756498540821</Y><Confidence>0.11174788</Confidence></Keypoint><Keypoint><ID>4</ID><X>-1.7974769397813526</X><Y>-1.4761098505477168</Y><Confidence>0.0</Confidence></Keypoint><Keypoint><ID>5</ID><X>0.5019181543915218</X><Y>-0.05281205550609363</Y><Confidence>0.36932853</Confidence></Keypoint><Keypoint><ID>6</ID><X>0.7742420345412628</X><Y>0.6280256539813954</Y><Confidence>0.18759453</Confidence></Keypoint><Keypoint><ID>7</ID><X>-1.7974769397813526</X><Y>-1.4761098505477168</Y><Confidence>0.0</Confidence></Keypoint><Keypoint><ID>8</ID><X>-1.7974769397813526</X><Y>-1.4761098505477168</Y><Confidence>0.0</Confidence></Keypoint><Keypoint><ID>9</ID><X>-1.7974769397813526</X><Y>-1.4761098505477168</Y><Confidence>0.0</Confidence></Keypoint><Keypoint><ID>10</ID><X>-1.7974769397813526</X><Y>-1.4761098505477168</Y><Confidence>0.0</Confidence></Keypoint><Keypoint><ID>11</ID><X>-1.7974769397813526</X><Y>-1.4761098505477168</Y><Confidence>0.0</Confidence></Keypoint><Keypoint><ID>12</ID><X>-1.7974769397813526</X><Y>-1.4761098505477168</Y><Confidence>0.0</Confidence></Keypoint><Keypoint><ID>13</ID><X>-1.7974769397813526</X><Y>-1.4761098505477168</Y><Confidence>0.0</Confidence></Keypoint><Keypoint><ID>14</ID><X>-0.07218887633215569</X><Y>-0.8337572443012435</Y><Confidence>0.9549491</Confidence></Keypoint><Keypoint><ID>15</ID><X>0.15256389387870867</X><Y>-0.8339498588997406</Y><Confidence>0.8745525</Confidence></Keypoint><Keypoint><ID>16</ID><X>-0.20852759796085715</X><Y>-0.7037863986997466</Y><Confidence>0.8129798</Confidence></Keypoint><Keypoint><ID>17</ID><X>0.2888248216501531</X><Y>-0.6981316330307317</Y><Confidence>0.7534849</Confidence></Keypoint></Frame><Frame><Avg_x>329</Avg_x><Avg_y>275</Avg_y><Avg_dist>187.44786861986535</Avg_dist><Keypoint><ID>0</ID><X>0.03300120019618241</X><Y>-0.7047194548684218</Y><Confidence>0.87287873</Confidence></Keypoint><Keypoint><ID>1</ID><X>0.02161196589316698</X><Y>0.00822901320609976</Y><Confidence>0.5552259</Confidence></Keypoint><Keypoint><ID>2</ID><X>-0.4943561978446494</X><Y>0.04281317305017827</Y><Confidence>0.54476905</Confidence></Keypoint><Keypoint><ID>3</ID><X>-0.720443471862485</X><Y>0.6517997120823319</Y><Confidence>0.122143894</Confidence></Keypoint><Keypoint><ID>4</ID><X>-1.7551546593852987</X><Y>-1.4670745633159792</Y><Confidence>0.0</Confidence></Keypoint><Keypoint><ID>5</ID><X>0.5028059755557936</X><Y>-0.032470290866573326</Y><Confidence>0.38417238</Confidence></Keypoint><Keypoint><ID>6</ID><X>-1.7551546593852987</X><Y>-1.4670745633159792</Y><Confidence>0.0</Confidence></Keypoint><Keypoint><ID>7</ID><X>-1.7551546593852987</X><Y>-1.4670745633159792</Y><Confidence>0.0</Confidence></Keypoint><Keypoint><ID>8</ID><X>-1.7551546593852987</X><Y>-1.4670745633159792</Y><Confidence>0.0</Confidence></Keypoint><Keypoint><ID>9</ID><X>-1.7551546593852987</X><Y>-1.4670745633159792</Y><Confidence>0.0</Confidence></Keypoint><Keypoint><ID>10</ID><X>-1.7551546593852987</X><Y>-1.4670745633159792</Y><Confidence>0.0</Confidence></Keypoint><Keypoint><ID>11</ID><X>-1.7551546593852987</X><Y>-1.4670745633159792</Y><Confidence>0.0</Confidence></Keypoint><Keypoint><ID>12</ID><X>-1.7551546593852987</X><Y>-1.4670745633159792</Y><Confidence>0.0</Confidence></Keypoint><Keypoint><ID>13</ID><X>-1.7551546593852987</X><Y>-1.4670745633159792</Y><Confidence>0.0</Confidence></Keypoint><Keypoint><ID>14</ID><X>-0.07714091394481355</X><Y>-0.7974630955740699</Y><Confidence>0.9076543</Confidence></Keypoint><Keypoint><ID>15</ID><X>0.12603569325305605</X><Y>-0.7977420224090753</Y><Confidence>0.93994844</Confidence></Keypoint><Keypoint><ID>16</ID><X>-0.21609295879979126</X><Y>-0.6874192346622733</Y><Confidence>0.77367336</Confidence></Keypoint><Keypoint><ID>17</ID><X>0.2593090759133803</X><Y>-0.6876213579167074</Y><Confidence>0.7842479</Confidence></Keypoint></Frame><Frame><Avg_x>326</Avg_x><Avg_y>275</Avg_y><Avg_dist>191.88241227831696</Avg_dist><Keypoint><ID>0</ID><X>0.00855047638642622</X><Y>-0.6490967343673384</Y><Confidence>0.8075814</Confidence></Keypoint><Keypoint><ID>1</ID><X>0.008429921699083654</X><Y>0.02501907370166119</Y><Confidence>0.5747569</Confidence></Keypoint><Keypoint><ID>2</ID><X>-0.4957386076608651</X><Y>0.041861581399405885</Y><Confidence>0.5405697</Confidence></Keypoint><Keypoint><ID>3</ID><X>-0.7277370379936158</X><Y>0.6367649282066203</Y><Confidence>0.13463286</Confidence></Keypoint><Keypoint><ID>4</ID><X>-1.6989571692852776</X><Y>-1.4331693912682557</Y><Confidence>0.0</Confidence></Keypoint><Keypoint><ID>5</ID><X>0.5011292947982432</X><Y>-0.037223088712933644</Y><Confidence>0.39112842</Confidence></Keypoint><Keypoint><ID>6</ID><X>-1.6989571692852776</X><Y>-1.4331693912682557</Y><Confidence>0.0</Confidence></Keypoint><Keypoint><ID>7</ID><X>-1.6989571692852776</X><Y>-1.4331693912682557</Y><Confidence>0.0</Confidence></Keypoint><Keypoint><ID>8</ID><X>-1.6989571692852776</X><Y>-1.4331693912682557</Y><Confidence>0.0</Confidence></Keypoint><Keypoint><ID>9</ID><X>-1.6989571692852776</X><Y>-1.4331693912682557</Y><Confidence>0.0</Confidence></Keypoint><Keypoint><ID>10</ID><X>-1.6989571692852776</X><Y>-1.4331693912682557</Y><Confidence>0.0</Confidence></Keypoint><Keypoint><ID>11</ID><X>-1.6989571692852776</X><Y>-1.4331693912682557</Y><Confidence>0.0</Confidence></Keypoint><Keypoint><ID>12</ID><X>-1.6989571692852776</X><Y>-1.4331693912682557</Y><Confidence>0.0</Confidence></Keypoint><Keypoint><ID>13</ID><X>-1.6989571692852776</X><Y>-1.4331693912682557</Y><Confidence>0.0</Confidence></Keypoint><Keypoint><ID>14</ID><X>-0.09348984194791425</X><Y>-0.7452721784926492</Y><Confidence>0.9183126</Confidence></Keypoint><Keypoint><ID>15</ID><X>0.10471097045816156</X><Y>-0.7453509048386051</Y><Confidence>0.8500749</Confidence></Keypoint><Keypoint><ID>16</ID><X>-0.22379482699789977</X><Y>-0.6432107074229306</Y><Confidence>0.8546494</Confidence></Keypoint><Keypoint><ID>17</ID><X>0.2290734682550235</X><Y>-0.6434403656927494</Y><Confidence>0.8395877</Confidence></Keypoint></Frame><Frame><Avg_x>324</Avg_x><Avg_y>279</Avg_y><Avg_dist>204.52736931567242</Avg_dist><Keypoint><ID>0</ID><X>-0.009028711700161922</X><Y>-0.6179393678632694</Y><Confidence>0.83411616</Confidence></Keypoint><Keypoint><ID>1</ID><X>0.012328496186182099</X><Y>0.0145979839561286</Y><Confidence>0.5533476</Confidence></Keypoint><Keypoint><ID>2</ID><X>-0.4977214971161845</X><Y>0.025238464682652267</Y><Confidence>0.5370887</Confidence></Keypoint><Keypoint><ID>3</ID><X>-0.7103175171862581</X><Y>0.5778300882982987</Y><Confidence>0.13946885</Confidence></Keypoint><Keypoint><ID>4</ID><X>-1.5841400644034622</X><Y>-1.3641206110140924</Y><Confidence>0.0</Confidence></Keypoint><Keypoint><ID>5</ID><X>0.5011345321753401</X><Y>-0.022580284234158057</Y><Confidence>0.41792464</Confidence></Keypoint><Keypoint><ID>6</ID><X>1.1175354678458393</X><Y>0.4713721621871646</Y><Confidence>0.3641865</Confidence></Keypoint><Keypoint><ID>7</ID><X>-1.5841400644034622</X><Y>-1.3641206110140924</Y><Confidence>0.0</Confidence></Keypoint><Keypoint><ID>8</ID><X>-1.5841400644034622</X><Y>-1.3641206110140924</Y><Confidence>0.0</Confidence></Keypoint><Keypoint><ID>9</ID><X>-1.5841400644034622</X><Y>-1.3641206110140924</Y><Confidence>0.0</Confidence></Keypoint><Keypoint><ID>10</ID><X>-1.5841400644034622</X><Y>-1.3641206110140924</Y><Confidence>0.0</Confidence></Keypoint><Keypoint><ID>11</ID><X>-1.5841400644034622</X><Y>-1.3641206110140924</Y><Confidence>0.0</Confidence></Keypoint><Keypoint><ID>12</ID><X>-1.5841400644034622</X><Y>-1.3641206110140924</Y><Confidence>0.0</Confidence></Keypoint><Keypoint><ID>13</ID><X>-1.5841400644034622</X><Y>-1.3641206110140924</Y><Confidence>0.0</Confidence></Keypoint><Keypoint><ID>14</ID><X>-0.11512748876052281</X><Y>-0.7079492522365809</Y><Confidence>0.97703505</Confidence></Keypoint><Keypoint><ID>15</ID><X>0.08650657711817843</X><Y>-0.708097418006177</Y><Confidence>0.9087752</Confidence></Keypoint><Keypoint><ID>16</ID><X>-0.2268425393028552</X><Y>-0.6175703709365714</Y><Confidence>0.80672646</Confidence></Keypoint><Keypoint><ID>17</ID><X>0.18780764808025793</X><Y>-0.6124773031656661</Y><Confidence>0.7720861</Confidence></Keypoint></Frame><Frame><Avg_x>315</Avg_x><Avg_y>277</Avg_y><Avg_dist>193.031959791023</Avg_dist><Keypoint><ID>0</ID><X>0.014671623746773756</X><Y>-0.643989456510616</Y><Confidence>0.84764314</Confidence></Keypoint><Keypoint><ID>1</ID><X>0.014802052935703825</X><Y>0.0201653011845083</Y><Confidence>0.5581656</Confidence></Keypoint><Keypoint><ID>2</ID><X>-0.49769312198324</X><Y>0.04263390279752834</Y><Confidence>0.51160616</Confidence></Keypoint><Keypoint><ID>3</ID><X>-0.7285576083170545</X><Y>0.6225856313672251</Y><Confidence>0.12902597</Confidence></Keypoint><Keypoint><ID>4</ID><X>-1.6318541258194754</X><Y>-1.4349955328634754</Y><Confidence>0.0</Confidence></Keypoint><Keypoint><ID>5</ID><X>0.49872738592745885</X><Y>-0.041901127899721224</Y><Confidence>0.42586052</Confidence></Keypoint><Keypoint><ID>6</ID><X>1.3152425659072813</X><Y>0.4198496620140561</Y><Confidence>0.37540123</Confidence></Keypoint><Keypoint><ID>7</ID><X>-1.6318541258194754</X><Y>-1.4349955328634754</Y><Confidence>0.0</Confidence></Keypoint><Keypoint><ID>8</ID><X>-1.6318541258194754</X><Y>-1.4349955328634754</Y><Confidence>0.0</Confidence></Keypoint><Keypoint><ID>9</ID><X>-1.6318541258194754</X><Y>-1.4349955328634754</Y><Confidence>0.0</Confidence></Keypoint><Keypoint><ID>10</ID><X>-1.6318541258194754</X><Y>-1.4349955328634754</Y><Confidence>0.0</Confidence></Keypoint><Keypoint><ID>11</ID><X>-1.6318541258194754</X><Y>-1.4349955328634754</Y><Confidence>0.0</Confidence></Keypoint><Keypoint><ID>12</ID><X>-1.6318541258194754</X><Y>-1.4349955328634754</Y><Confidence>0.0</Confidence></Keypoint><Keypoint><ID>13</ID><X>-1.6318541258194754</X><Y>-1.4349955328634754</Y><Confidence>0.0</Confidence></Keypoint><Keypoint><ID>14</ID><X>-0.08137247858166519</X><Y>-0.7342098560293308</Y><Confidence>0.9395121</Confidence></Keypoint><Keypoint><ID>15</ID><X>0.10470981764095279</X><Y>-0.7341347604357044</Y><Confidence>0.96753377</Confidence></Keypoint><Keypoint><ID>16</ID><X>-0.2107576016163482</X><Y>-0.6384492198048332</Y><Confidence>0.814153</Confidence></Keypoint><Keypoint><ID>17</ID><X>0.2286499568017685</X><Y>-0.6384334892541682</Y><Confidence>0.8019587</Confidence></Keypoint></Frame><Frame><Avg_x>311</Avg_x><Avg_y>278</Avg_y><Avg_dist>193.4504619020058</Avg_dist><Keypoint><ID>0</ID><X>0.007263150476036969</X><Y>-0.6422044175519716</Y><Confidence>0.799418</Confidence></Keypoint><Keypoint><ID>1</ID><X>0.02970081296181465</X><Y>0.02045911220949229</Y><Confidence>0.5662719</Confidence></Keypoint><Keypoint><ID>2</ID><X>-0.4927381324103993</X><Y>0.05413674496997369</Y><Confidence>0.5035259</Confidence></Keypoint><Keypoint><ID>3</ID><X>-0.7286268531390042</X><Y>0.6160628496334953</Y><Confidence>0.12463217</Confidence></Keypoint><Keypoint><ID>4</ID><X>-1.6076467171091071</X><Y>-1.4370604095058899</Y><Confidence>0.0</Confidence></Keypoint><Keypoint><ID>5</ID><X>0.5015517677684703</X><Y>-0.05257592720298536</Y><Confidence>0.45040053</Confidence></Keypoint><Keypoint><ID>6</ID><X>0.9284925339764729</X><Y>0.2227036440189946</Y><Confidence>0.051704235</Confidence></Keypoint><Keypoint><ID>7</ID><X>-1.6076467171091071</X><Y>-1.4370604095058899</Y><Confidence>0.0</Confidence></Keypoint><Keypoint><ID>8</ID><X>-1.6076467171091071</X><Y>-1.4370604095058899</Y><Confidence>0.0</Confidence></Keypoint><Keypoint><ID>9</ID><X>-1.6076467171091071</X><Y>-1.4370604095058899</Y><Confidence>0.0</Confidence></Keypoint><Keypoint><ID>10</ID><X>-1.6076467171091071</X><Y>-1.4370604095058899</Y><Confidence>0.0</Confidence></Keypoint><Keypoint><ID>11</ID><X>-1.6076467171091071</X><Y>-1.4370604095058899</Y><Confidence>0.0</Confidence></Keypoint><Keypoint><ID>12</ID><X>-1.6076467171091071</X><Y>-1.4370604095058899</Y><Confidence>0.0</Confidence></Keypoint><Keypoint><ID>13</ID><X>-1.6076467171091071</X><Y>-1.4370604095058899</Y><Confidence>0.0</Confidence></Keypoint><Keypoint><ID>14</ID><X>-0.09929555382340474</X><Y>-0.7323050446747936</Y><Confidence>0.91973764</Confidence></Keypoint><Keypoint><ID>15</ID><X>0.10825313967797634</X><Y>-0.732229717154707</Y><Confidence>0.87935215</Confidence></Keypoint><Keypoint><ID>16</ID><X>-0.21744381119233955</X><Y>-0.6312278175281256</Y><Confidence>0.7956773</Confidence></Keypoint><Keypoint><ID>17</ID><X>0.22087306696541337</X><Y>-0.620060808463977</Y><Confidence>0.7626334</Confidence></Keypoint></Frame><Frame><Avg_x>309</Avg_x><Avg_y>279</Avg_y><Avg_dist>191.52012872839302</Avg_dist><Keypoint><ID>0</ID><X>0.0007262898266480146</X><Y>-0.631519999004551</Y><Confidence>0.83382076</Confidence></Keypoint><Keypoint><ID>1</ID><X>0.0403202394570397</X><Y>0.02097731529147824</Y><Confidence>0.5847246</Confidence></Keypoint><Keypoint><ID>2</ID><X>-0.49282477452627005</X><Y>0.060832270348822416</Y><Confidence>0.51079834</Confidence></Keypoint><Keypoint><ID>3</ID><X>-0.7029407559978829</X><Y>0.617016988659658</Y><Confidence>0.14133178</Confidence></Keypoint><Keypoint><ID>4</ID><X>-1.6134074368664022</X><Y>-1.4567659381415088</Y><Confidence>0.0</Confidence></Keypoint><Keypoint><ID>5</ID><X>0.5000613810372879</X><Y>-0.05823528228504239</Y><Confidence>0.4161338</Confidence></Keypoint><Keypoint><ID>6</ID><X>1.4533894393642663</X><Y>0.29914265398630036</Y><Confidence>0.17388651</Confidence></Keypoint><Keypoint><ID>7</ID><X>-1.6134074368664022</X><Y>-1.4567659381415088</Y><Confidence>0.0</Confidence></Keypoint><Keypoint><ID>8</ID><X>-1.6134074368664022</X><Y>-1.4567659381415088</Y><Confidence>0.0</Confidence></Keypoint><Keypoint><ID>9</ID><X>-1.6134074368664022</X><Y>-1.4567659381415088</Y><Confidence>0.0</Confidence></Keypoint><Keypoint><ID>10</ID><X>-1.6134074368664022</X><Y>-1.4567659381415088</Y><Confidence>0.0</Confidence></Keypoint><Keypoint><ID>11</ID><X>-1.6134074368664022</X><Y>-1.4567659381415088</Y><Confidence>0.0</Confidence></Keypoint><Keypoint><ID>12</ID><X>-1.6134074368664022</X><Y>-1.4567659381415088</Y><Confidence>0.0</Confidence></Keypoint><Keypoint><ID>13</ID><X>-1.6134074368664022</X><Y>-1.4567659381415088</Y><Confidence>0.0</Confidence></Keypoint><Keypoint><ID>14</ID><X>-0.09585894369549053</X><Y>-0.7391556573474721</Y><Confidence>0.9212785</Confidence></Keypoint><Keypoint><ID>15</ID><X>0.09158517900910913</X><Y>-0.7392189965765402</Y><Confidence>0.9257498</Confidence></Keypoint><Keypoint><ID>16</ID><X>-0.22050847502994916</X><Y>-0.6257419475457979</Y><Confidence>0.8065756</Confidence></Keypoint><Keypoint><ID>17</ID><X>0.22219242213131296</X><Y>-0.6202438634467246</Y><Confidence>0.81876814</Confidence></Keypoint></Frame><Frame><Avg_x>309</Avg_x><Avg_y>280</Avg_y><Avg_dist>191.53510727229383</Avg_dist><Keypoint><ID>0</ID><X>0.0007002619925374724</X><Y>-0.6367076799446761</Y><Confidence>0.8373423</Confidence></Keypoint><Keypoint><ID>1</ID><X>0.04038496153322194</X><Y>0.01596661075589991</Y><Confidence>0.5869044</Confidence></Keypoint><Keypoint><ID>2</ID><X>-0.4928116477222835</X><Y>0.06122440790181208</Y><Confidence>0.5292808</Confidence></Keypoint><Keypoint><ID>3</ID><X>-0.691480993947773</X><Y>0.6117635351797833</Y><Confidence>0.16569287</Confidence></Keypoint><Keypoint><ID>4</ID><X>-1.6132812642055927</X><Y>-1.46187299021866</Y><Confidence>0.0</Confidence></Keypoint><Keypoint><ID>5</ID><X>0.5000740576769716</X><Y>-0.05784689852347093</Y><Confidence>0.4167605</Confidence></Keypoint><Keypoint><ID>6</ID><X>0.9424600703473232</X><Y>0.14648795758384967</Y><Confidence>0.10215418</Confidence></Keypoint><Keypoint><ID>7</ID><X>-1.6132812642055927</X><Y>-1.46187299021866</Y><Confidence>0.0</Confidence></Keypoint><Keypoint><ID>8</ID><X>-1.6132812642055927</X><Y>-1.46187299021866</Y><Confidence>0.0</Confidence></Keypoint><Keypoint><ID>9</ID><X>-1.6132812642055927</X><Y>-1.46187299021866</Y><Confidence>0.0</Confidence></Keypoint><Keypoint><ID>10</ID><X>-1.6132812642055927</X><Y>-1.46187299021866</Y><Confidence>0.0</Confidence></Keypoint><Keypoint><ID>11</ID><X>-1.6132812642055927</X><Y>-1.46187299021866</Y><Confidence>0.0</Confidence></Keypoint><Keypoint><ID>12</ID><X>-1.6132812642055927</X><Y>-1.46187299021866</Y><Confidence>0.0</Confidence></Keypoint><Keypoint><ID>13</ID><X>-1.6132812642055927</X><Y>-1.46187299021866</Y><Confidence>0.0</Confidence></Keypoint><Keypoint><ID>14</ID><X>-0.09597365454583198</X><Y>-0.738630374796849</Y><Confidence>0.8876621</Confidence></Keypoint><Keypoint><ID>15</ID><X>0.09150711428717374</X><Y>-0.744237330348246</Y><Confidence>0.9248106</Confidence></Keypoint><Keypoint><ID>16</ID><X>-0.2204896373781663</X><Y>-0.6251588540049506</Y><Confidence>0.819224</Confidence></Keypoint><Keypoint><ID>17</ID><X>0.2220818371714375</X><Y>-0.6253073509735616</Y><Confidence>0.82443476</Confidence></Keypoint></Frame><Frame><Avg_x>315</Avg_x><Avg_y>284</Avg_y><Avg_dist>193.82147514704673</Avg_dist><Keypoint><ID>0</ID><X>-0.019019571305969755</X><Y>-0.6441537501631556</Y><Confidence>0.82328993</Confidence></Keypoint><Keypoint><ID>1</ID><X>0.025838029991729385</X><Y>0.0007891494038339052</Y><Confidence>0.5739985</Confidence></Keypoint><Keypoint><ID>2</ID><X>-0.4955743316119862</X><Y>0.06237460820606575</Y><Confidence>0.5071482</Confidence></Keypoint><Keypoint><ID>3</ID><X>-0.6974136197741413</X><Y>0.5839037991907958</Y><Confidence>0.20877361</Confidence></Keypoint><Keypoint><ID>4</ID><X>-1.6252069063091108</X><Y>-1.4652659091802775</Y><Confidence>0.0</Confidence></Keypoint><Keypoint><ID>5</ID><X>0.49679363986882774</X><Y>-0.060937228934796854</Y><Confidence>0.40491903</Confidence></Keypoint><Keypoint><ID>6</ID><X>1.264813458198683</X><Y>0.29224113891200665</Y><Confidence>0.3349253</Confidence></Keypoint><Keypoint><ID>7</ID><X>-1.6252069063091108</X><Y>-1.4652659091802775</Y><Confidence>0.0</Confidence></Keypoint><Keypoint><ID>8</ID><X>-1.6252069063091108</X><Y>-1.4652659091802775</Y><Confidence>0.0</Confidence></Keypoint><Keypoint><ID>9</ID><X>-1.6252069063091108</X><Y>-1.4652659091802775</Y><Confidence>0.0</Confidence></Keypoint><Keypoint><ID>10</ID><X>-1.6252069063091108</X><Y>-1.4652659091802775</Y><Confidence>0.0</Confidence></Keypoint><Keypoint><ID>11</ID><X>-1.6252069063091108</X><Y>-1.4652659091802775</Y><Confidence>0.0</Confidence></Keypoint><Keypoint><ID>12</ID><X>-1.6252069063091108</X><Y>-1.4652659091802775</Y><Confidence>0.0</Confidence></Keypoint><Keypoint><ID>13</ID><X>-1.6252069063091108</X><Y>-1.4652659091802775</Y><Confidence>0.0</Confidence></Keypoint><Keypoint><ID>14</ID><X>-0.11981719009016557</X><Y>-0.733814474367946</Y><Confidence>0.9130947</Confidence></Keypoint><Keypoint><ID>15</ID><X>0.08179599700576738</X><Y>-0.7283859231766684</Y><Confidence>0.887434</Confidence></Keypoint><Keypoint><ID>16</ID><X>-0.22108779467027462</X><Y>-0.6326159828019942</Y><Confidence>0.8078619</Confidence></Keypoint><Keypoint><ID>17</ID><X>0.19965653114193377</X><Y>-0.6159873200549266</Y><Confidence>0.7525255</Confidence></Keypoint></Frame><Frame><Avg_x>319</Avg_x><Avg_y>281</Avg_y><Avg_dist>190.81192065562067</Avg_dist><Keypoint><ID>0</ID><X>-0.00048252505863769727</X><Y>-0.6330145005168807</Y><Confidence>0.8528533</Confidence></Keypoint><Keypoint><ID>1</ID><X>0.03371613859346092</X><Y>0.010764291198724421</Y><Confidence>0.60954213</Confidence></Keypoint><Keypoint><ID>2</ID><X>-0.4902431405128079</X><Y>0.09038972232015761</Y><Confidence>0.5338871</Confidence></Keypoint><Keypoint><ID>3</ID><X>-0.6896748895742576</X><Y>0.6088672960494699</Y><Confidence>0.22243933</Confidence></Keypoint><Keypoint><ID>4</ID><X>-1.6718033071724827</X><Y>-1.4726543238729393</Y><Confidence>0.0</Confidence></Keypoint><Keypoint><ID>5</ID><X>0.4950777473192479</X><Y>-0.08032274940305745</Y><Confidence>0.43996802</Confidence></Keypoint><Keypoint><ID>6</ID><X>0.8653068937937161</X><Y>0.3011999144613953</Y><Confidence>0.08395477</Confidence></Keypoint><Keypoint><ID>7</ID><X>-1.6718033071724827</X><Y>-1.4726543238729393</Y><Confidence>0.0</Confidence></Keypoint><Keypoint><ID>8</ID><X>-1.6718033071724827</X><Y>-1.4726543238729393</Y><Confidence>0.0</Confidence></Keypoint><Keypoint><ID>9</ID><X>-1.6718033071724827</X><Y>-1.4726543238729393</Y><Confidence>0.0</Confidence></Keypoint><Keypoint><ID>10</ID><X>-1.6718033071724827</X><Y>-1.4726543238729393</Y><Confidence>0.0</Confidence></Keypoint><Keypoint><ID>11</ID><X>-1.6718033071724827</X><Y>-1.4726543238729393</Y><Confidence>0.0</Confidence></Keypoint><Keypoint><ID>12</ID><X>-1.6718033071724827</X><Y>-1.4726543238729393</Y><Confidence>0.0</Confidence></Keypoint><Keypoint><ID>13</ID><X>-1.6718033071724827</X><Y>-1.4726543238729393</Y><Confidence>0.0</Confidence></Keypoint><Keypoint><ID>14</ID><X>-0.09746398430015848</X><Y>-0.7238925055695609</Y><Confidence>0.98594975</Confidence></Keypoint><Keypoint><ID>15</ID><X>0.0908928790435498</X><Y>-0.7239364878006267</Y><Confidence>0.89417183</Confidence></Keypoint><Keypoint><ID>16</ID><X>-0.22247348014294607</X><Y>-0.6100810456914989</Y><Confidence>0.7702943</Confidence></Keypoint><Keypoint><ID>17</ID><X>0.22151306815185579</X><Y>-0.5986213554357785</Y><Confidence>0.7908217</Confidence></Keypoint></Frame><Frame><Avg_x>327</Avg_x><Avg_y>279</Avg_y><Avg_dist>191.36383307824283</Avg_dist><Keypoint><ID>0</ID><X>-0.0025506290121795456</X><Y>-0.637513247918089</Y><Confidence>0.8342062</Confidence></Keypoint><Keypoint><ID>1</ID><X>0.03705763824410465</X><Y>0.015515396225081917</Y><Confidence>0.4267223</Confidence></Keypoint><Keypoint><ID>2</ID><X>-0.4907911606054322</X><Y>0.09493669550266459</Y><Confidence>0.44038633</Confidence></Keypoint><Keypoint><ID>3</ID><X>-0.6897084084692838</X><Y>0.6175836081606119</Y><Confidence>0.11195961</Confidence></Keypoint><Keypoint><ID>4</ID><X>-1.7087868420063455</X><Y>-1.4579557459320196</Y><Confidence>0.0</Confidence></Keypoint><Keypoint><ID>5</ID><X>0.49151692730759733</X><Y>-0.09233535372157964</Y><Confidence>0.3634287</Confidence></Keypoint><Keypoint><ID>6</ID><X>0.7698954227151034</X><Y>0.4186868527206732</Y><Confidence>0.19327706</Confidence></Keypoint><Keypoint><ID>7</ID><X>-1.7087868420063455</X><Y>-1.4579557459320196</Y><Confidence>0.0</Confidence></Keypoint><Keypoint><ID>8</ID><X>-1.7087868420063455</X><Y>-1.4579557459320196</Y><Confidence>0.0</Confidence></Keypoint><Keypoint><ID>9</ID><X>-1.7087868420063455</X><Y>-1.4579557459320196</Y><Confidence>0.0</Confidence></Keypoint><Keypoint><ID>10</ID><X>-1.7087868420063455</X><Y>-1.4579557459320196</Y><Confidence>0.0</Confidence></Keypoint><Keypoint><ID>11</ID><X>-1.7087868420063455</X><Y>-1.4579557459320196</Y><Confidence>0.0</Confidence></Keypoint><Keypoint><ID>12</ID><X>-1.7087868420063455</X><Y>-1.4579557459320196</Y><Confidence>0.0</Confidence></Keypoint><Keypoint><ID>13</ID><X>-1.7087868420063455</X><Y>-1.4579557459320196</Y><Confidence>0.0</Confidence></Keypoint><Keypoint><ID>14</ID><X>-0.09919943862480786</X><Y>-0.7342233753283404</Y><Confidence>0.8835562</Confidence></Keypoint><Keypoint><ID>15</ID><X>0.08837258141173536</X><Y>-0.7172137863728836</Y><Confidence>0.9288799</Confidence></Keypoint><Keypoint><ID>16</ID><X>-0.18970099948587402</X><Y>-0.6998229745429978</Y><Confidence>0.053710096</Confidence></Keypoint><Keypoint><ID>17</ID><X>0.21890932173776426</X><Y>-0.6035000502865274</Y><Confidence>0.7872165</Confidence></Keypoint></Frame><Frame><Avg_x>349</Avg_x><Avg_y>271</Avg_y><Avg_dist>152.02430633197477</Avg_dist><Keypoint><ID>0</ID><X>-0.1335807814207037</X><Y>-0.7856357503757162</Y><Confidence>0.8568293</Confidence></Keypoint><Keypoint><ID>1</ID><X>-0.019108376905184663</X><Y>0.014857676919185384</Y><Confidence>0.5266473</Confidence></Keypoint><Keypoint><ID>2</ID><X>-0.4909693984300974</X><Y>0.08639630527387414</Y><Confidence>0.119591996</Confidence></Keypoint><Keypoint><ID>3</ID><X>-2.2956855283252557</X><Y>-1.782609679587806</Y><Confidence>0.0</Confidence></Keypoint><Keypoint><ID>4</ID><X>-2.2956855283252557</X><Y>-1.782609679587806</Y><Confidence>0.0</Confidence></Keypoint><Keypoint><ID>5</ID><X>0.49543408879083456</X><Y>-0.07794529140324445</Y><Confidence>0.46098843</Confidence></Keypoint><Keypoint><ID>6</ID><X>0.7242847500866456</X><Y>0.5869193903029646</Y><Confidence>0.3699777</Confidence></Keypoint><Keypoint><ID>7</ID><X>-0.17641619427607286</X><Y>0.42961779591670757</Y><Confidence>0.07921972</Confidence></Keypoint><Keypoint><ID>8</ID><X>-2.2956855283252557</X><Y>-1.782609679587806</Y><Confidence>0.0</Confidence></Keypoint><Keypoint><ID>9</ID><X>-2.2956855283252557</X><Y>-1.782609679587806</Y><Confidence>0.0</Confidence></Keypoint><Keypoint><ID>10</ID><X>-2.2956855283252557</X><Y>-1.782609679587806</Y><Confidence>0.0</Confidence></Keypoint><Keypoint><ID>11</ID><X>-2.2956855283252557</X><Y>-1.782609679587806</Y><Confidence>0.0</Confidence></Keypoint><Keypoint><ID>12</ID><X>-2.2956855283252557</X><Y>-1.782609679587806</Y><Confidence>0.0</Confidence></Keypoint><Keypoint><ID>13</ID><X>-2.2956855283252557</X><Y>-1.782609679587806</Y><Confidence>0.0</Confidence></Keypoint><Keypoint><ID>14</ID><X>-0.26199708782181813</X><Y>-0.8997669948144369</Y><Confidence>0.9673235</Confidence></Keypoint><Keypoint><ID>15</ID><X>0.0022093602855210413</X><Y>-0.8932288461228668</Y><Confidence>0.9068043</Confidence></Keypoint><Keypoint><ID>16</ID><X>-0.390789182198082</X><Y>-0.7356667897185776</Y><Confidence>0.81904566</Confidence></Keypoint><Keypoint><ID>17</ID><X>0.16654051840777437</X><Y>-0.7283432401441162</Y><Confidence>0.7559788</Confidence></Keypoint></Frame><Frame><Avg_x>347</Avg_x><Avg_y>274</Avg_y><Avg_dist>170.08388495169658</Avg_dist><Keypoint><ID>0</ID><X>-0.10120469295726728</X><Y>-0.7645560648406817</Y><Confidence>0.82606673</Confidence></Keypoint><Keypoint><ID>1</ID><X>-0.005412942543830438</X><Y>-0.010598551548711222</Y><Confidence>0.56701374</Confidence></Keypoint><Keypoint><ID>2</ID><X>-0.49093547955328476</X><Y>0.0914478317252197</Y><Confidence>0.36130407</Confidence></Keypoint><Keypoint><ID>3</ID><X>-2.0401697673977</X><Y>-1.6109697875128814</Y><Confidence>0.0</Confidence></Keypoint><Keypoint><ID>4</ID><X>-2.0401697673977</X><Y>-1.6109697875128814</Y><Confidence>0.0</Confidence></Keypoint><Keypoint><ID>5</ID><X>0.4929403927057895</X><Y>-0.08740481149384435</Y><Confidence>0.4118236</Confidence></Keypoint><Keypoint><ID>6</ID><X>0.8252218229470184</X><Y>0.5707562862923351</Y><Confidence>0.42481384</Confidence></Keypoint><Keypoint><ID>7</ID><X>0.10331887692683617</X><Y>0.5709132845927147</Y><Confidence>0.4370247</Confidence></Keypoint><Keypoint><ID>8</ID><X>-2.0401697673977</X><Y>-1.6109697875128814</Y><Confidence>0.0</Confidence></Keypoint><Keypoint><ID>9</ID><X>-2.0401697673977</X><Y>-1.6109697875128814</Y><Confidence>0.0</Confidence></Keypoint><Keypoint><ID>10</ID><X>-2.0401697673977</X><Y>-1.6109697875128814</Y><Confidence>0.0</Confidence></Keypoint><Keypoint><ID>11</ID><X>-2.0401697673977</X><Y>-1.6109697875128814</Y><Confidence>0.0</Confidence></Keypoint><Keypoint><ID>12</ID><X>-2.0401697673977</X><Y>-1.6109697875128814</Y><Confidence>0.0</Confidence></Keypoint><Keypoint><ID>13</ID><X>-2.0401697673977</X><Y>-1.6109697875128814</Y><Confidence>0.0</Confidence></Keypoint><Keypoint><ID>14</ID><X>-0.22228196163664024</X><Y>-0.8606019730741045</Y><Confidence>0.9209237</Confidence></Keypoint><Keypoint><ID>15</ID><X>0.020065997628173335</X><Y>-0.8666533604205928</Y><Confidence>0.9061892</Confidence></Keypoint><Keypoint><ID>16</ID><X>-0.3313320839471622</X><Y>-0.7071169358037465</Y><Confidence>0.82738537</Confidence></Keypoint><Keypoint><ID>17</ID><X>0.17997388022371788</X><Y>-0.7198066150001994</Y><Confidence>0.82117224</Confidence></Keypoint></Frame><Frame><Avg_x>341</Avg_x><Avg_y>272</Avg_y><Avg_dist>179.91421588439323</Avg_dist><Keypoint><ID>0</ID><X>-0.0383446224183538</X><Y>-0.7299940311294231</Y><Confidence>0.8042358</Confidence></Keypoint><Keypoint><ID>1</ID><X>0.01603242097929719</X><Y>0.007141295368600595</Y><Confidence>0.5690835</Confidence></Keypoint><Keypoint><ID>2</ID><X>-0.49114339044389427</X><Y>0.09169985722949972</Y><Confidence>0.49776536</Confidence></Keypoint><Keypoint><ID>3</ID><X>-0.6663649045061879</X><Y>0.6050867518220232</Y><Confidence>0.24554959</Confidence></Keypoint><Keypoint><ID>4</ID><X>-1.8953477262692517</X><Y>-1.511831617434711</Y><Confidence>0.0</Confidence></Keypoint><Keypoint><ID>5</ID><X>0.4933881804229461</X><Y>-0.0835074085058905</Y><Confidence>0.39173648</Confidence></Keypoint><Keypoint><ID>6</ID><X>0.7832212006213772</X><Y>0.6413100697611551</Y><Confidence>0.19787806</Confidence></Keypoint><Keypoint><ID>7</ID><X>-1.8953477262692517</X><Y>-1.511831617434711</Y><Confidence>0.0</Confidence></Keypoint><Keypoint><ID>8</ID><X>-1.8953477262692517</X><Y>-1.511831617434711</Y><Confidence>0.0</Confidence></Keypoint><Keypoint><ID>9</ID><X>-1.8953477262692517</X><Y>-1.511831617434711</Y><Confidence>0.0</Confidence></Keypoint><Keypoint><ID>10</ID><X>-1.8953477262692517</X><Y>-1.511831617434711</Y><Confidence>0.0</Confidence></Keypoint><Keypoint><ID>11</ID><X>-1.8953477262692517</X><Y>-1.511831617434711</Y><Confidence>0.0</Confidence></Keypoint><Keypoint><ID>12</ID><X>-1.8953477262692517</X><Y>-1.511831617434711</Y><Confidence>0.0</Confidence></Keypoint><Keypoint><ID>13</ID><X>-1.8953477262692517</X><Y>-1.511831617434711</Y><Confidence>0.0</Confidence></Keypoint><Keypoint><ID>14</ID><X>-0.14706495424872973</X><Y>-0.8264178024077066</Y><Confidence>0.8455329</Confidence></Keypoint><Keypoint><ID>15</ID><X>0.06448063377865607</X><Y>-0.8446367478863968</Y><Confidence>0.9005705</Confidence></Keypoint><Keypoint><ID>16</ID><X>-0.26782308683725503</X><Y>-0.6995909002959444</Y><Confidence>0.770057</Confidence></Keypoint><Keypoint><ID>17</ID><X>0.2336998705099291</X><Y>-0.7056621293518014</Y><Confidence>0.7439824</Confidence></Keypoint></Frame><Frame><Avg_x>344</Avg_x><Avg_y>274</Avg_y><Avg_dist>181.0001453668021</Avg_dist><Keypoint><ID>0</ID><X>-0.04242226581495998</X><Y>-0.7662800066898618</Y><Confidence>0.8588319</Confidence></Keypoint><Keypoint><ID>1</ID><X>0.017598512119965173</X><Y>0.0018027275317997994</Y><Confidence>0.54833454</Confidence></Keypoint><Keypoint><ID>2</ID><X>-0.4869180214602208</X><Y>0.09200502878180976</Y><Confidence>0.4862895</Confidence></Keypoint><Keypoint><ID>3</ID><X>-0.7088764040366765</X><Y>0.6805478526234323</Y><Confidence>0.105087265</Confidence></Keypoint><Keypoint><ID>4</ID><X>-1.900550959795496</X><Y>-1.5138109389068777</Y><Confidence>0.0</Confidence></Keypoint><Keypoint><ID>5</ID><X>0.49781902649585347</X><Y>-0.0820436609080477</Y><Confidence>0.37236768</Confidence></Keypoint><Keypoint><ID>6</ID><X>0.7200867997401779</X><Y>0.6804714744367595</Y><Confidence>0.08139608</Confidence></Keypoint><Keypoint><ID>7</ID><X>-1.900550959795496</X><Y>-1.5138109389068777</Y><Confidence>0.0</Confidence></Keypoint><Keypoint><ID>8</ID><X>-1.900550959795496</X><Y>-1.5138109389068777</Y><Confidence>0.0</Confidence></Keypoint><Keypoint><ID>9</ID><X>-1.900550959795496</X><Y>-1.5138109389068777</Y><Confidence>0.0</Confidence></Keypoint><Keypoint><ID>10</ID><X>-1.900550959795496</X><Y>-1.5138109389068777</Y><Confidence>0.0</Confidence></Keypoint><Keypoint><ID>11</ID><X>-1.900550959795496</X><Y>-1.5138109389068777</Y><Confidence>0.0</Confidence></Keypoint><Keypoint><ID>12</ID><X>-1.900550959795496</X><Y>-1.5138109389068777</Y><Confidence>0.0</Confidence></Keypoint><Keypoint><ID>13</ID><X>-1.900550959795496</X><Y>-1.5138109389068777</Y><Confidence>0.0</Confidence></Keypoint><Keypoint><ID>14</ID><X>-0.14471305900730533</X><Y>-0.8624428413951829</Y><Confidence>0.98275983</Confidence></Keypoint><Keypoint><ID>15</ID><X>0.08932066430053547</X><Y>-0.8684381918384585</Y><Confidence>0.93274677</Confidence></Keypoint><Keypoint><ID>16</ID><X>-0.2469559683033702</X><Y>-0.7304215439812398</Y><Confidence>0.8044298</Confidence></Keypoint><Keypoint><ID>17</ID><X>0.2575804606985098</X><Y>-0.7306192336586655</Y><Confidence>0.7359204</Confidence></Keypoint></Frame><Frame><Avg_x>348</Avg_x><Avg_y>277</Avg_y><Avg_dist>184.83437507448227</Avg_dist><Keypoint><ID>0</ID><X>-0.0514445866658301</X><Y>-0.766794407982002</Y><Confidence>0.8342195</Confidence></Keypoint><Keypoint><ID>1</ID><X>0.013079171381274905</X><Y>-0.01431896508332996</Y><Confidence>0.54208946</Confidence></Keypoint><Keypoint><ID>2</ID><X>-0.4925864330208554</X><Y>0.056285544362494666</Y><Confidence>0.46300805</Confidence></Keypoint><Keypoint><ID>3</ID><X>-0.7100652192357783</X><Y>0.6501967552792702</Y><Confidence>0.085691676</Confidence></Keypoint><Keypoint><ID>4</ID><X>-1.882766665344405</X><Y>-1.4986389836218397</Y><Confidence>0.0</Confidence></Keypoint><Keypoint><ID>5</ID><X>0.501144625423615</X><Y>-0.055511519475660985</Y><Confidence>0.32963184</Confidence></Keypoint><Keypoint><ID>6</ID><X>0.6893140710191669</X><Y>0.6501437557083075</Y><Confidence>0.12359143</Confidence></Keypoint><Keypoint><ID>7</ID><X>-1.882766665344405</X><Y>-1.4986389836218397</Y><Confidence>0.0</Confidence></Keypoint><Keypoint><ID>8</ID><X>-1.882766665344405</X><Y>-1.4986389836218397</Y><Confidence>0.0</Confidence></Keypoint><Keypoint><ID>9</ID><X>-1.882766665344405</X><Y>-1.4986389836218397</Y><Confidence>0.0</Confidence></Keypoint><Keypoint><ID>10</ID><X>-1.882766665344405</X><Y>-1.4986389836218397</Y><Confidence>0.0</Confidence></Keypoint><Keypoint><ID>11</ID><X>-1.882766665344405</X><Y>-1.4986389836218397</Y><Confidence>0.0</Confidence></Keypoint><Keypoint><ID>12</ID><X>-1.882766665344405</X><Y>-1.4986389836218397</Y><Confidence>0.0</Confidence></Keypoint><Keypoint><ID>13</ID><X>-1.882766665344405</X><Y>-1.4986389836218397</Y><Confidence>0.0</Confidence></Keypoint><Keypoint><ID>14</ID><X>-0.15741599049821794</X><Y>-0.8610898494789719</Y><Confidence>0.9348646</Confidence></Keypoint><Keypoint><ID>15</ID><X>0.06616245194681154</X><Y>-0.8670513931199497</Y><Confidence>0.922904</Confidence></Keypoint><Keypoint><ID>16</ID><X>-0.2631114993677433</X><Y>-0.7433075077682937</Y><Confidence>0.7821953</Confidence></Keypoint><Keypoint><ID>17</ID><X>0.24822538934280208</X><Y>-0.7609054291741649</Y><Confidence>0.7235729</Confidence></Keypoint></Frame><Frame><Avg_x>348</Avg_x><Avg_y>273</Avg_y><Avg_dist>181.47590450865889</Avg_dist><Keypoint><ID>0</ID><X>-0.040545841507943374</X><Y>-0.7591376834676857</Y><Confidence>0.8443587</Confidence></Keypoint><Keypoint><ID>1</ID><X>0.013420100102442508</X><Y>0.0013695215181481102</Y><Confidence>0.556372</Confidence></Keypoint><Keypoint><ID>2</ID><X>-0.49567312263867186</X><Y>0.05542694393721186</Y><Confidence>0.50276256</Confidence></Keypoint><Keypoint><ID>3</ID><X>-0.7053600006170698</X><Y>0.6842485338107596</Y><Confidence>0.114959836</Confidence></Keypoint><Keypoint><ID>4</ID><X>-1.9176099490574279</X><Y>-1.5043319427950512</Y><Confidence>0.0</Confidence></Keypoint><Keypoint><ID>5</ID><X>0.49850297383064096</X><Y>-0.05234081195034373</Y><Confidence>0.3370327</Confidence></Keypoint><Keypoint><ID>6</ID><X>0.7378241685150033</X><Y>0.6842224685068165</Y><Confidence>0.08342992</Confidence></Keypoint><Keypoint><ID>7</ID><X>-1.9176099490574279</X><Y>-1.5043319427950512</Y><Confidence>0.0</Confidence></Keypoint><Keypoint><ID>8</ID><X>-1.9176099490574279</X><Y>-1.5043319427950512</Y><Confidence>0.0</Confidence></Keypoint><Keypoint><ID>9</ID><X>-1.9176099490574279</X><Y>-1.5043319427950512</Y><Confidence>0.0</Confidence></Keypoint><Keypoint><ID>10</ID><X>-1.9176099490574279</X><Y>-1.5043319427950512</Y><Confidence>0.0</Confidence></Keypoint><Keypoint><ID>11</ID><X>-1.9176099490574279</X><Y>-1.5043319427950512</Y><Confidence>0.0</Confidence></Keypoint><Keypoint><ID>12</ID><X>-1.9176099490574279</X><Y>-1.5043319427950512</Y><Confidence>0.0</Confidence></Keypoint><Keypoint><ID>13</ID><X>-1.9176099490574279</X><Y>-1.5043319427950512</Y><Confidence>0.0</Confidence></Keypoint><Keypoint><ID>14</ID><X>-0.1601544764054895</X><Y>-0.8607371272179093</Y><Confidence>0.92761755</Confidence></Keypoint><Keypoint><ID>15</ID><X>0.07307450001272968</X><Y>-0.8669796413898536</Y><Confidence>0.90554297</Confidence></Keypoint><Keypoint><ID>16</ID><X>-0.26788624535727845</X><Y>-0.758937316953826</Y><Confidence>0.822404</Confidence></Keypoint><Keypoint><ID>17</ID><X>0.25871075387953835</X><Y>-0.7650577866461785</Y><Confidence>0.7944627</Confidence></Keypoint></Frame></data>